kochen/__init__.py
kochen/fitutil.py
kochen/importutil.py
kochen/ipcutil.py
kochen/logging.py
kochen/misc.py
kochen/pathutil.py
kochen/plotutil.py
kochen/prototyping.py
kochen/scriptutil.py
kochen/template.py
kochen/versioning.py
kochen/datautil/__init__.py
kochen/datautil/deprec.py
kochen/datautil/latest.py
kochen/demo/__init__.py
kochen/demo/colorgrid.py
kochen/demo/curve_fitting.py
kochen/demo/ipcutil_usage.py
kochen/demo/live_plotter.py
kochen/demo/sign_csr.py
kochen/lib/typing.py
kochen/mathutil/__init__.py
kochen/mathutil/deprec.py
kochen/mathutil/latest.py
kochen/patches/matplotlib_legend_valigntext_top.patch
kochen/recipe/__init__.py
kochen/recipe/ansi.py
kochen/recipe/plotutil.py
kochen/sampleutil/__init__.py
kochen/sampleutil/deprec.py
kochen/sampleutil/latest.py
kochen/templates/default.py
kochen/templates/kochen.py
kochen-0.2026.7.dist-info/METADATA
kochen-0.2026.7.dist-info/WHEEL
kochen-0.2026.7.dist-info/RECORD
