Metadata-Version: 2.4
Name: kochen
Version: 0.2026.7
Summary: A compilation of boilerplate scribbles
Author-email: Justin Peh Yu Xiang <pehyuxiang@gmail.com>
License-Expression: GPL-2.0-or-later
Keywords: boilerplate,recipe,script
Classifier: Development Status :: 3 - Alpha
Classifier: Intended Audience :: Education
Classifier: Intended Audience :: Science/Research
Classifier: License :: OSI Approved :: GNU General Public License v2 or later (GPLv2+)
Classifier: Natural Language :: English
Classifier: Operating System :: OS Independent
Classifier: Programming Language :: Python :: 3
Classifier: Topic :: Scientific/Engineering
Requires-Python: >=3.8
Requires-Dist: configargparse
Requires-Dist: pyreadline3; platform_system == 'Windows'
Requires-Dist: sortedcontainers
Requires-Dist: typing-extensions
Provides-Extra: all
Requires-Dist: arrow; extra == 'all'
Requires-Dist: matplotlib; extra == 'all'
Requires-Dist: numpy; extra == 'all'
Requires-Dist: polars; extra == 'all'
Requires-Dist: scipy; extra == 'all'
Requires-Dist: tqdm; extra == 'all'
Requires-Dist: uncertainties; extra == 'all'
Provides-Extra: datautil
Requires-Dist: numpy; extra == 'datautil'
Requires-Dist: polars; extra == 'datautil'
Requires-Dist: tqdm; extra == 'datautil'
Provides-Extra: dev
Requires-Dist: pytest; extra == 'dev'
Provides-Extra: fitutil
Requires-Dist: numpy; extra == 'fitutil'
Requires-Dist: scipy; extra == 'fitutil'
Requires-Dist: uncertainties; extra == 'fitutil'
Provides-Extra: mathutil
Requires-Dist: numpy; extra == 'mathutil'
Requires-Dist: scipy; extra == 'mathutil'
Requires-Dist: uncertainties; extra == 'mathutil'
Provides-Extra: plotutil
Requires-Dist: arrow; extra == 'plotutil'
Requires-Dist: matplotlib; extra == 'plotutil'
